partools/__init__.py
partools/changelog.py
partools/conf.py
partools/crypto.py
partools/dq/__init__.py
partools/dq/csf.py
partools/dq/empty_al.py
partools/dq/fill_al.py
partools/dq/functions.py
partools/dq/gl.py
partools/dq/gstf.py
partools/dq/init.py
partools/dq/main.py
partools/dq/sort.py
partools/mail/__init__.py
partools/mail/functions.py
partools/mail/get.py
partools/mail/gl.py
partools/mail/main.py
partools/mail/files/confidential.txt
partools/mail/files/test/recipients.txt
partools/mail/files/test/template.html
partools/quickstart/__init__.py
partools/quickstart/dq.py
partools/quickstart/mail.py
partools/quickstart/reqlist.py
partools/quickstart/sql_connect.py
partools/quickstart/sql_download.py
partools/quickstart/sql_execute.py
partools/quickstart/sql_upload.py
partools/quickstart/tools_bf.py
partools/quickstart/tools_dup.py
partools/quickstart/tools_extract_doc.py
partools/quickstart/tools_filter.py
partools/quickstart/tools_split.py
partools/quickstart/tools_xml.py
partools/quickstart/utils_log.py
partools/quickstart/utils_sTools.py
partools/quickstart/files/create_table.sql
partools/quickstart/files/in.csv
partools/quickstart/files/in_11.csv
partools/quickstart/files/in_12.csv
partools/quickstart/files/insert_table.sql
partools/quickstart/files/xml_in.xml
partools/rl/__init__.py
partools/rl/functions.py
partools/rl/gl.py
partools/rl/init.py
partools/rl/join.py
partools/rl/main.py
partools/rl/ql.py
partools/sql/__init__.py
partools/sql/connect.py
partools/sql/download.py
partools/sql/execute.py
partools/sql/functions.py
partools/sql/gl.py
partools/sql/gls.py
partools/sql/groupby.py
partools/sql/init.py
partools/sql/iutd.py
partools/sql/log.py
partools/sql/merge.py
partools/sql/process.py
partools/sql/recover.py
partools/sql/rg.py
partools/sql/upload.py
partools/sql/ranges/RG_DR.csv
partools/sql/ranges/RG_IN.csv
partools/sql/ranges/RG_INSTANCE_CODE.csv
partools/sql/ranges/RG_PRM_2.csv
partools/sql/ranges/RG_PRM_3.csv
partools/sql/ranges/RG_PRM_TEST.csv
ParTools-2.0.3.dist-info/LICENSE
ParTools-2.0.3.dist-info/METADATA
ParTools-2.0.3.dist-info/WHEEL
ParTools-2.0.3.dist-info/top_level.txt
ParTools-2.0.3.dist-info/RECORD
