Metadata-Version: 2.1
Name: ParTools
Version: 2.0.3
Summary: This package contains a bunch of Python tools developed for Support, Test and Automation IT Engineers
Home-page: https://github.com/paularnaud2/ParTools
Author: Paul Arnaud
Author-email: paularnaud2pro@gmail.com
License: UNKNOWN
Project-URL: Bug Tracker, https://github.com/paularnaud2/ParTools/issues
Platform: UNKNOWN
Classifier: Programming Language :: Python :: 3
Classifier: License :: OSI Approved :: MIT License
Classifier: Operating System :: OS Independent
Requires-Python: >=3.6
License-File: LICENSE
Requires-Dist: wheel
Requires-Dist: twine
Requires-Dist: pytest
Requires-Dist: cx-Oracle
Requires-Dist: pandas
Requires-Dist: pywin32
Requires-Dist: cryptography
